lha_arducon/__init__.py
lha_arducon/lha_arducon.py
lha_arducon-0.1.0.dist-info/METADATA
lha_arducon-0.1.0.dist-info/WHEEL
lha_arducon-0.1.0.dist-info/top_level.txt
lha_arducon-0.1.0.dist-info/RECORD
