Metadata-Version: 2.4
Name: lha_arducon
Version: 0.1.0
Summary: Arduino 시리얼 통신을 쉽게 제어하는 Python 라이브러리
Author-email: Lee Hyuna <lha110@naver.com>
License: MIT
Classifier: Programming Language :: Python :: 3
Classifier: License :: OSI Approved :: MIT License
Classifier: Operating System :: OS Independent
Requires-Python: >=3.7
Requires-Dist: pyserial>=3.5
